[
  {
    "name": "section_title",
    "label": "Section Title",
    "required": false,
    "locked": false,
    "validation_regex": "",
    "allow_new_line": false,
    "show_emoji_picker": false,
    "type": "text",
    "default": "Lorem Ipsum"
  },
  {
    "name": "section_intro",
    "label": "Section Intro",
    "required": false,
    "locked": false,
    "validation_regex": "",
    "allow_new_line": false,
    "show_emoji_picker": false,
    "type": "text",
    "default": "Lorem ipsum dolor, sit amet consectetur adipisicing elit. Esse vero, recusandae inventore corrupti qui saepe laboriosam accusamus."
  },
  {
    "name": "is_on_dark_background",
    "label": "Is On Dark Background?",
    "sortable": false,
    "required": false,
    "locked": false,
    "type": "boolean",
    "default": false
  },
  {
    "name": "is_centered",
    "label": "Is Centered?",
    "sortable": false,
    "required": false,
    "locked": false,
    "type": "boolean",
    "default": true
  },
  {
    "name": "hide_button",
    "label": "Hide Button",
    "sortable": false,
    "required": false,
    "locked": false,
    "type": "boolean",
    "default": true
  },
  {
    "name": "button_text",
    "label": "Button Text",
    "required": false,
    "locked": false,
    "validation_regex": "",
    "allow_new_line": false,
    "show_emoji_picker": false,
    "type": "text",
    "default": "CTA BUTTON HERE"
  },
  {
    "name": "button_url",
    "label": "Button URL",
    "required": false,
    "locked": false,
    "validation_regex": "",
    "allow_new_line": false,
    "show_emoji_picker": false,
    "type": "text",
    "default": "https://google.com"
  }
]